{
    "workload": "job_11",
    "iterations": 100,
    "early_stopped": false,
    "best_cost": -0.22862707207778338,
    "best_performance": 0.22862707207778338,
    "configuration": {
        "shared_buffers": 19091.0,
        "work_mem": 236946.0,
        "maintenance_work_mem": 1304542.0,
        "effective_cache_size": 2217994.0,
        "max_connections": 183.0,
        "max_wal_senders": 5.0,
        "wal_buffers": 4557.0,
        "autovacuum_max_workers": 5.0,
        "autovacuum_analyze_scale_factor": 0.05762382538185379,
        "autovacuum_analyze_threshold": 3668.0,
        "autovacuum_naptime": 41.0,
        "autovacuum_vacuum_cost_delay": 10.0,
        "autovacuum_vacuum_cost_limit": 365.0,
        "autovacuum_vacuum_scale_factor": 0.03405754159269458,
        "autovacuum_vacuum_threshold": 4269.0,
        "backend_flush_after": 60.0,
        "bgwriter_delay": 705.0,
        "bgwriter_flush_after": 159.0,
        "bgwriter_lru_maxpages": 140.0,
        "bgwriter_lru_multiplier": 2.0,
        "checkpoint_completion_target": 0.5018160097823079,
        "checkpoint_flush_after": 126.0,
        "checkpoint_timeout": 1190.0,
        "commit_delay": 460.0,
        "commit_siblings": 92.0,
        "cursor_tuple_fraction": 0.2523673742028679,
        "deadlock_timeout": 1750.0,
        "default_statistics_target": 378.0,
        "effective_io_concurrency": 63.0,
        "from_collapse_limit": 15.0,
        "geqo_effort": 5.0,
        "geqo_generations": 391.0,
        "geqo_pool_size": 76.0,
        "geqo_seed": 0.8732488707979215,
        "geqo_threshold": 13.0,
        "join_collapse_limit": 18.0,
        "temp_buffers": 2486.0,
        "vacuum_cost_delay": 35.0,
        "vacuum_cost_limit": 190.0,
        "vacuum_cost_page_dirty": 43.0,
        "vacuum_cost_page_hit": 55.0,
        "vacuum_cost_page_miss": 50.0,
        "wal_writer_delay": 2069.0,
        "temp_file_limit": -1
    }
}